Metadata-Version: 2.1
Name: correios
Version: 6.1.7
Summary: A client library for Brazilian Correios APIs and services
Home-page: https://github.com/osantana/correios
Author: Osvaldo Santana Neto
Author-email: correiospy@osantana.me
License: UNKNOWN
Platform: UNKNOWN
Classifier: Development Status :: 2 - Pre-Alpha
Classifier: Programming Language :: Python
Classifier: Programming Language :: Python :: 3
Classifier: Programming Language :: Python :: 3.5
Requires-Dist: phonenumbers
Requires-Dist: Pillow
Provides-Extra: api
Requires-Dist: requests; extra == 'api'
Requires-Dist: zeep; extra == 'api'
Requires-Dist: lxml; extra == 'api'
Provides-Extra: pdf
Requires-Dist: reportlab; extra == 'pdf'
Requires-Dist: hubarcode; extra == 'pdf'
